devoir/__init__.py
devoir/__main__.py
test/__init__.py
test/test_doctest.py
devoir-1.1.0.dist-info/AUTHORS
devoir-1.1.0.dist-info/LICENSE
devoir-1.1.0.dist-info/METADATA
devoir-1.1.0.dist-info/WHEEL
devoir-1.1.0.dist-info/entry_points.txt
devoir-1.1.0.dist-info/top_level.txt
devoir-1.1.0.dist-info/zip-safe
devoir-1.1.0.dist-info/RECORD
