Metadata-Version: 2.1
Name: devoir
Version: 1.1.0
Summary: "Quickly set up a working environment to edit a file.
Home-page: http://framagit.org/spalax/devoir
Author: Louis Paternault
Author-email: spalax@gresille.org
License: GPLv3 or any later version
Project-URL: Documentation, http://devoir.readthedocs.io
Project-URL: Source, https://framagit.org/spalax/devoir
Project-URL: Tracker, https://framagit.org/spalax/devoir/issues
Keywords: work setup
Classifier: Development Status :: 5 - Production/Stable
Classifier: Environment :: Console
Classifier: License :: OSI Approved :: GNU General Public License v3 or later (GPLv3+)
Classifier: Intended Audience :: End Users/Desktop
Classifier: Operating System :: POSIX :: Linux
Classifier: Programming Language :: Python
Classifier: Programming Language :: Python :: 3
Classifier: Programming Language :: Python :: 3.8
Classifier: Programming Language :: Python :: 3.9
Classifier: Programming Language :: Python :: 3.10
Classifier: Programming Language :: Python :: 3.11
Classifier: Programming Language :: Python :: 3.12
Classifier: Programming Language :: Python :: 3.13
Classifier: Topic :: Utilities
Requires-Python: <4,>=3.8
License-File: LICENSE
License-File: AUTHORS
